reverse_unique/__init__.py
reverse_unique/models.py
reverse_unique/fields.py
django_reverse_unique-1.0.dist-info/DESCRIPTION.rst
django_reverse_unique-1.0.dist-info/METADATA
django_reverse_unique-1.0.dist-info/WHEEL
django_reverse_unique-1.0.dist-info/top_level.txt
django_reverse_unique-1.0.dist-info/RECORD
django_reverse_unique-1.0.dist-info/metadata.json
